pysidocast.cp312-win_amd64.pyd
pysidocast-1.3.3.dist-info/LICENSE
pysidocast-1.3.3.dist-info/METADATA
pysidocast-1.3.3.dist-info/WHEEL
pysidocast-1.3.3.dist-info/top_level.txt
pysidocast-1.3.3.dist-info/RECORD
