Metadata-Version: 2.1
Name: pysidocast
Version: 1.3.3
Summary: A simple 3D Ray Caster for pygame.
Author: Yvant2000
Author-email: Yvant2000 <yvant2000@gmail.com>
Project-URL: Homepage, https://github.com/Yvant2000/PySiDoCast
Project-URL: Bug Tracker, https://github.com/Yvant2000/PySiDoCast/issues
Classifier: Programming Language :: Python :: 3.10
Classifier: License :: OSI Approved :: MIT License
Classifier: Operating System :: Microsoft :: Windows
Requires-Python: >=3.10
License-File: LICENSE
